alibabacloud_gws20190618/__init__.py
alibabacloud_gws20190618/client.py
alibabacloud_gws20190618/models.py
alibabacloud_gws20190618-2.0.0.dist-info/LICENSE
alibabacloud_gws20190618-2.0.0.dist-info/METADATA
alibabacloud_gws20190618-2.0.0.dist-info/WHEEL
alibabacloud_gws20190618-2.0.0.dist-info/top_level.txt
alibabacloud_gws20190618-2.0.0.dist-info/RECORD
